ltiaas/__init__.py
ltiaas/client/base.py
ltiaas/client/enums.py
ltiaas/client/launch.py
ltiaas/client/request_handler.py
ltiaas/exceptions/__init__.py
ltiaas/exceptions/api_error.py
ltiaas/exceptions/invalid_session_error.py
ltiaas/exceptions/validation_error.py
ltiaas/resources/__init__.py
ltiaas/resources/deep_linking/enums.py
ltiaas/resources/deep_linking/types.py
ltiaas/resources/idtoken/__init__.py
ltiaas/resources/idtoken/enums.py
ltiaas/resources/idtoken/types.py
ltiaas/resources/lineitems/__init__.py
ltiaas/resources/lineitems/types.py
ltiaas/resources/memberships/__init__.py
ltiaas/resources/memberships/enums.py
ltiaas/resources/memberships/types.py
ltiaas/resources/scores/enums.py
ltiaas/resources/scores/types.py
ltiaas/utils/__init__.py
ltiaas/utils/serialization.py
ltiaas/utils/validation.py
ltiaas-0.0.3.dist-info/LICENSE
ltiaas-0.0.3.dist-info/METADATA
ltiaas-0.0.3.dist-info/WHEEL
ltiaas-0.0.3.dist-info/RECORD
